odoo8_addon_field_rrule-8.0.1.0.1.99.dev3-nspkg.pth
odoo_addons/field_rrule/README.rst
odoo_addons/field_rrule/__init__.py
odoo_addons/field_rrule/__openerp__.py
odoo_addons/field_rrule/field_rrule.py
odoo_addons/field_rrule/hooks.py
odoo_addons/field_rrule/demo/__init__.py
odoo_addons/field_rrule/demo/res_partner.py
odoo_addons/field_rrule/demo/res_partner.xml
odoo_addons/field_rrule/i18n/ca.po
odoo_addons/field_rrule/i18n/de.po
odoo_addons/field_rrule/i18n/field_rrule.pot
odoo_addons/field_rrule/i18n/fr.po
odoo_addons/field_rrule/i18n/fr_CH.po
odoo_addons/field_rrule/i18n/it.po
odoo_addons/field_rrule/i18n/nl.po
odoo_addons/field_rrule/i18n/sl.po
odoo_addons/field_rrule/static/description/icon.png
odoo_addons/field_rrule/static/src/css/field_rrule.css
odoo_addons/field_rrule/static/src/js/field_rrule.js
odoo_addons/field_rrule/static/src/xml/field_rrule.xml
odoo_addons/field_rrule/tests/__init__.py
odoo_addons/field_rrule/tests/test_field_rrule.py
odoo_addons/field_rrule/views/templates.xml
odoo8_addon_field_rrule-8.0.1.0.1.99.dev3.dist-info/METADATA
odoo8_addon_field_rrule-8.0.1.0.1.99.dev3.dist-info/WHEEL
odoo8_addon_field_rrule-8.0.1.0.1.99.dev3.dist-info/namespace_packages.txt
odoo8_addon_field_rrule-8.0.1.0.1.99.dev3.dist-info/top_level.txt
odoo8_addon_field_rrule-8.0.1.0.1.99.dev3.dist-info/RECORD
