Metadata-Version: 2.1
Name: odoo8-addon-field-rrule
Version: 8.0.1.0.1.99.dev3
Summary: Provides a field and widget for RRules according to RFC 2445
Home-page: UNKNOWN
Author: Therp BV,Odoo Community Association (OCA)
Author-email: support@odoo-community.org
License: AGPL-3
Platform: UNKNOWN
Classifier: Programming Language :: Python
Classifier: Framework :: Odoo
Classifier: License :: OSI Approved :: GNU Affero General Public License v3
Requires-Python: ~=2.7
Requires-Dist: odoo (<9.0a,>=8.0a)
